{"hyomin":[{},{"Date":"2023-06-12","breakfast":"북어해장국 생선조림 연두부&양념장 얼갈이나물 김치","lunch":"쇠고기미역국 탕수육&소스 해물부추전 무말랭이지 김치","dinner":"청량시락국 닭볶음탕  비빔만두 미역줄기무침 깍두기"},{"Date":"2023-06-13","breakfast":"순두부찌개 그릴소시지구기&소스 진미채볶음 도시락김 깍두기","lunch":"<특식> 쑥갓우동 흰쌀밥 치즈스틱 콩나물매콤무침 김치","dinner":"육개장 고기산적파채무침 떡볶이 열무된장나물 김치"},{"Date":"2023-06-14","breakfast":"오징어두부국 계란후라이*깨간장 치킨너겟 궁채나물 깍두기","lunch":"촌된장찌개 치킨유린기&소스 브로컬리새우살볶음 시금치나물 깍두기","dinner":"<특식> 돈불야채비빔밥 미소두부국 새우볼꼬지튀김&케챱 숙주나물 김치/음료캔"},{"Date":"2023-06-15","breakfast":"쇠고기해장국 소불고기 야채고로케&케찹 오이생채 김치","lunch":"<특식> 카레라이스 유부장국 초코츄러스 단배추나물 김치","dinner":"부대찌개 순대야채볶음 오미산적 참나물무침 깍두기"},{"Date":"2023-06-16","breakfast":"모듬어묵국 스팸구이 감자채볶음 열무나물 김치","lunch":"쇠고기두부국 깐풍땅콩강정 마카로니샐러드 오징어젓갈 김치","dinner":"순두부찌개 간장불고기 고구마샐러드 상추겉절이 깍두기"},{"Date":"2023-06-17","breakfast":"없음","lunch":"아욱국 등심까스&어니언소스 볼어묵조림 가지나물 김치","dinner":"버섯찌개 고등어신김치조림 김말이튀김&간장 시금치나물 깍두기"},{"Date":"2023-06-18","breakfast":"없음","lunch":"콩나물국 함박데리야끼조림 청포묵김무침 오복지 김치","dinner":"김치찌개 생선가스&타르s 메란곤약조림 고사리나물 깍두기"}],"happy":[{"Date":"2023-06-12","breakfast":"오징어볼*칠리s / 멸치볶음 / 동원양반김 / 두부된장국 / 쌀밥 / 포기김치","lunch_s":"카레라이스 / 야채튀김 / 고들빼기지 / 어묵국 / 쌀밥 / 포기김치","dinner":"함박스테이크 / 청미채오리엔탈무침 / 푸실리파스타 / 건새우무국 / 쌀밥 / 포기김치"},{"Date":"2023-06-13","breakfast":"소고기야채죽 / 김치도토리묵무침 / 동원양반김 / 무말랭이지 / 쌀밥 / 깍두기 ","lunch_s":"순살양념치킨 / 콘샐러드 / 치킨무절임 / 우동국물 / 후리가케조미밥 / 캔콜라 / 포기김치 ","dinner":"탕)돈육김치찌개 / 볼어묵볶음 / 오복채무침 / 숙주나물 / 쌀밥 / 깍두기 "},{"Date":"2023-06-14","breakfast":"떡갈비조림 / 오이지무침 / 동원양반김 / 맑은감자국 / 쌀밥 / 포기김치 ","lunch_s":"마라마파두부덮밥 / 교자만두튀김 / 부추무침 / 계란파국 / 쌀밥 / 포기김치 ","dinner":"탕)닭개장 / 알감자버터구이 / 우엉채볶음 / 간장고추지 / 쌀밥 / 포기김치 "},{"Date":"2023-06-15","breakfast":"꼬지없는 소떡소떡 / 빨간콩나물무침 / 동원양반김 / 얼큰버섯국 / 쌀밥 / 포기김치 ","lunch":"오삼불고기 / 마카로니샐러드 / 양념깻잎지 / 팽이버섯장국 / 쌀밥 / 포기김치 ","dinner":"후르츠탕수육 / 진미채조림 / 중국식오이무침 / 야채짬뽕국 / 쌀밥 / 포기김치 "},{"Date":"2023-06-16","breakfast":"가자미구이 / 치커리무침 / 동원양반김 / 미역국 / 쌀밥 / 포기김치 ","lunch":"탕)부대찌개*라면사리 / 건파래볶음 / 두부쑥갓무침 / 명엽채볶음 / 쌀밥 / 깍두기 ","dinner_s":"치킨너겟*머스타드 / 쫄면야채무침 / 콩자반 / 유부김치국 / 쌀밥 / 깍두기 "},{"Date":"2023-06-17","breakfast":"즉석토스트 / 딸기잼 / 씨리얼&우유 / 그린샐러드&드레싱 / 신선한과일","lunch_s":"참치김치볶음 / 김구이*양념장 / 땅콩조림 / 들깨무채국 / 쌀밥 / 깍두기 ","dinner":"생선까스*타르s / 얼갈이유자무침 / 마늘쫑지 / 콩나물국 / 쌀밥 / 포기김치 "},{"Date":"2023-06-18","breakfast":"모닝빵 / 딸기잼 / 씨리얼&우유 / 그린샐러드&드레싱 / 신선한과일","lunch":"매콤완자조림 / 감자샐러드 / 청포묵김가루무침 / 배추된장국 / 쌀밥 / 포기김치 ","dinner":"순대야채볶음 / 호박나물 / 고추잎무침 / 감자수제비국 / 쌀밥 / 포기김치 "}],"inforamtion":null,"suduck":null}